How2jGongjuHeZhongjianjianJiaochengFix1/README.md
How2jGongjuHeZhongjianjianJiaochengFix1/__init__.py
How2jGongjuHeZhongjianjianJiaochengFix1/__main__.py
How2jGongjuHeZhongjianjianJiaochengFix1/file.epub
How2jGongjuHeZhongjianjianJiaochengFix1/index.html
How2jGongjuHeZhongjianjianJiaochengFix1/css/__init__.py
How2jGongjuHeZhongjianjianJiaochengFix1/css/annotations.css
How2jGongjuHeZhongjianjianJiaochengFix1/css/main.css
How2jGongjuHeZhongjianjianJiaochengFix1/css/normalize.css
How2jGongjuHeZhongjianjianJiaochengFix1/css/popup.css
How2jGongjuHeZhongjianjianJiaochengFix1/font/__init__.py
How2jGongjuHeZhongjianjianJiaochengFix1/font/fontello.eot
How2jGongjuHeZhongjianjianJiaochengFix1/font/fontello.svg
How2jGongjuHeZhongjianjianJiaochengFix1/font/fontello.ttf
How2jGongjuHeZhongjianjianJiaochengFix1/font/fontello.woff
How2jGongjuHeZhongjianjianJiaochengFix1/img/__init__.py
How2jGongjuHeZhongjianjianJiaochengFix1/img/annotator-glyph-sprite.png
How2jGongjuHeZhongjianjianJiaochengFix1/img/annotator-icon-sprite.png
How2jGongjuHeZhongjianjianJiaochengFix1/img/apple-touch-icon.png
How2jGongjuHeZhongjianjianJiaochengFix1/img/cancelfullscreen.png
How2jGongjuHeZhongjianjianJiaochengFix1/img/close.png
How2jGongjuHeZhongjianjianJiaochengFix1/img/fullscreen.png
How2jGongjuHeZhongjianjianJiaochengFix1/img/loader.gif
How2jGongjuHeZhongjianjianJiaochengFix1/img/menu-icon.png
How2jGongjuHeZhongjianjianJiaochengFix1/img/save.png
How2jGongjuHeZhongjianjianJiaochengFix1/img/saved.png
How2jGongjuHeZhongjianjianJiaochengFix1/img/settings-s.png
How2jGongjuHeZhongjianjianJiaochengFix1/img/settings.png
How2jGongjuHeZhongjianjianJiaochengFix1/img/star.png
How2jGongjuHeZhongjianjianJiaochengFix1/js/__init__.py
How2jGongjuHeZhongjianjianJiaochengFix1/js/epub.js
How2jGongjuHeZhongjianjianJiaochengFix1/js/epub.min.js
How2jGongjuHeZhongjianjianJiaochengFix1/js/epub.min.map
How2jGongjuHeZhongjianjianJiaochengFix1/js/hooks.min.js
How2jGongjuHeZhongjianjianJiaochengFix1/js/hooks.min.map
how2j_gongju_he_zhongjianjian_jiaocheng_fix1-2025.3.25.0.dist-info/METADATA
how2j_gongju_he_zhongjianjian_jiaocheng_fix1-2025.3.25.0.dist-info/WHEEL
how2j_gongju_he_zhongjianjian_jiaocheng_fix1-2025.3.25.0.dist-info/entry_points.txt
how2j_gongju_he_zhongjianjian_jiaocheng_fix1-2025.3.25.0.dist-info/top_level.txt
how2j_gongju_he_zhongjianjian_jiaocheng_fix1-2025.3.25.0.dist-info/RECORD
